ecmtool/__init__.py
ecmtool/_bglu_dense.c
ecmtool/_bglu_dense.py
ecmtool/bglu_dense_uncompiled.py
ecmtool/conversion_cone.py
ecmtool/custom_redund.py
ecmtool/helpers.py
ecmtool/intersect_directly_mpi.py
ecmtool/mpi_wrapper.py
ecmtool/network.py
ecmtool/nullspace.py
ecmtool/efmtool/.DS_Store
ecmtool/efmtool/CalculateFluxModes.m
ecmtool/efmtool/CreateFluxModeOpts.m
ecmtool/efmtool/LICENSE.txt
ecmtool/efmtool/SignToDouble.m
ecmtool/efmtool/e_coli_core-2.xml
ecmtool/efmtool/e_coli_core.mat
ecmtool/efmtool/java.opts
ecmtool/polco/polco.jar
ecmtool/redund/cyggcc_s-1.dll
ecmtool/redund/cyggmp-10.dll
ecmtool/redund/cygstdc++-6.dll
ecmtool/redund/cygwin1.dll
ecmtool/redund/redund_mac
ecmtool/redund/redund_win.exe
ecmtool-0.1.7.dist-info/LICENSE
ecmtool-0.1.7.dist-info/METADATA
ecmtool-0.1.7.dist-info/WHEEL
ecmtool-0.1.7.dist-info/top_level.txt
ecmtool-0.1.7.dist-info/RECORD
